{
  "narrative_summary": "In the past 48 hours, several drone incidents have been reported across multiple regions, with a notable emphasis on drone terrorism linked to Iran's military actions in the Gulf. Attacks including drone strikes near military bases in Cyprus and Dubai have raised concerns over security in these areas. Various smuggling schemes involving drones persist, particularly in prisons across Europe, where gangs have been caught using drones for contraband deliveries. The FAA's restriction of airspace in Texas responds to increased drone-related incidents. A rise in airport disruptions and travel cancellations reflects a broader threat from drone activity amidst escalating tensions in the region, prompting authorities to enhance security measures.",
  "totals": {
    "other": 38,
    "smuggling": 8,
    "crash": 5,
    "terrorism": 6,
    "airport": 6,
    "interference": 3,
    "total_incidents": 113,
    "by_category": {
      "airport": 10,
      "crash": 14,
      "interference": 2,
      "other": 70,
      "security": 1,
      "smuggling": 11,
      "terrorism": 5
    },
    "by_query": {
      "drone airport disruption": 10,
      "drone crash": 27,
      "drone illegal": 5,
      "drone incident": 26,
      "drone prison": 8,
      "drone security breach": 2,
      "drone smuggling": 3,
      "drone terrorism": 31,
      "unauthorized drone": 1
    }
  },
  "clusters": [
    {
      "topic": "Iran-related Drone Activities",
      "rationale": "Multiple incidents link drone activity to Iranian military actions and terrorism, highlighting a pattern of cross-border tensions and targeted strikes.",
      "incident_ids": [
        "5be8ae3f96e8",
        "bf6c683983bc",
        "3c2c50aa3b62",
        "a4d6eed4928a",
        "5da5cd02e883",
        "ce989d18c394",
        "b8fb31b2345c",
        "0b63bc32164c"
      ]
    },
    {
      "topic": "Prison Smuggling Operations",
      "rationale": "Several reports indicate the use of drones for transporting contraband into prisons, showing a growing trend of drone-related criminal activity.",
      "incident_ids": [
        "5da5cd02e883",
        "ce989d18c394",
        "7e1431fcf52e",
        "0b63bc32164c",
        "af08590f2d39"
      ]
    }
  ],
  "highlights": [
    {
      "id": "5be8ae3f96e8",
      "headline": "Australian troops safe after drone strikes air base near Dubai",
      "one_sentence": "A drone strike near a military base in Dubai has raised security concerns for Australian troops stationed there.",
      "risk_tags": [
        "terrorism",
        "security"
      ],
      "countries": [
        "Australia"
      ],
      "priority_score": 0.9
    },
    {
      "id": "5da5cd02e883",
      "headline": "Air defenses intercept drone near Abu Ghraib prison",
      "one_sentence": "A drone was intercepted near the Abu Ghraib prison, highlighting ongoing security risks in the area.",
      "risk_tags": [
        "smuggling",
        "security"
      ],
      "countries": [
        "Iraq"
      ],
      "priority_score": 0.8
    },
    {
      "id": "ce989d18c394",
      "headline": "Gang jailed for drone smuggling scheme likened to ‘Uber Eats for prisoners’",
      "one_sentence": "A criminal gang has been sentenced for using drones to deliver contraband to prisoners, concerning authorities about new smuggling methods.",
      "risk_tags": [
        "smuggling",
        "crime"
      ],
      "countries": [],
      "priority_score": 0.7
    },
    {
      "id": "d64ee7ced7c9",
      "headline": "Drone strikes damage Amazon data centres in UAE and Bahrain, disrupting services",
      "one_sentence": "Drone strikes have reportedly damaged Amazon's facilities in the UAE and Bahrain, causing significant disruptions.",
      "risk_tags": [
        "interference"
      ],
      "countries": [
        "UAE",
        "Bahrain"
      ],
      "priority_score": 0.8
    },
    {
      "id": "e0cc0e8761aa",
      "headline": "Iran launches retaliatory strikes at targets across the Middle East",
      "one_sentence": "Iran has initiated drone and missile strikes across multiple countries in retaliation for attacks, escalating regional tensions.",
      "risk_tags": [
        "terrorism",
        "conflict"
      ],
      "countries": [],
      "priority_score": 0.9
    }
  ],
  "draft_social": {
    "twitter": "Drone-related incidents surge as tensions rise in the Middle East, highlighting new security threats and smuggling methods. #DroneSecurity #IranWar",
    "linkedin": "Recent drone incidents reveal escalating tensions in the Middle East and emerging challenges in security, particularly in smuggling and military operations."
  },
  "window_hours": 48,
  "date_utc": "2026-03-03"
}